{"code": 0, "message": "Success", "ttl": 1, "data": {"count": 2053, "events": [{"event_index": "1044385-6", "block_num": 1044385, "extrinsic_idx": 6, "module_id": "plasmlockdrop", "event_id": "ClaimComplete", "params": "[{\"type\":\"ClaimId\",\"value\":\"0x247ba19d7b1dcdf59ea16913b0cc65a5fc41942f986b4ffa52c2b8817789224f\",\"value_raw\":\"\"},{\"type\":\"AccountId\",\"value\":\"1ce3e414c73563b07f7290b9bbc018e7bb116b0808115165e0d1ebd991f02fc7\",\"value_raw\":\"\"},{\"type\":\"Balance\",\"value\":\"8775000000000000000\",\"value_raw\":\"\"}]", "event_idx": 13, "extrinsic_hash": "", "block_timestamp": 1598898090}, {"event_index": "1044382-1", "block_num": 1044382, "extrinsic_idx": 1, "module_id": "plasmlockdrop", "event_id": "ClaimComplete", "params": "[{\"type\":\"ClaimId\",\"value\":\"0x49a28046c6b723c6f8da82bc6b5b1af3f1e6ba61158baba077a445bffb6840ff\",\"value_raw\":\"\"},{\"type\":\"AccountId\",\"value\":\"10b32ba26429421c283b305fd1e7f585ae328d85dbaec2c0829b9e5f5ed64f78\",\"value_raw\":\"\"},{\"type\":\"Balance\",\"value\":\"4656000000000000000\",\"value_raw\":\"\"}]", "event_idx": 3, "extrinsic_hash": "", "block_timestamp": 1598898060}, {"event_index": "1044350-1", "block_num": 1044350, "extrinsic_idx": 1, "module_id": "plasmlockdrop", "event_id": "ClaimComplete", "params": "[{\"type\":\"ClaimId\",\"value\":\"0x6bd058f8e7226d1421445e8a208fb1bf02d39fdc91e55f32936dbbe79f0e6791\",\"value_raw\":\"\"},{\"type\":\"AccountId\",\"value\":\"ec927e3f2902be19dbdf16e59136931f8ea64d4babc692517692b7045f2a2135\",\"value_raw\":\"\"},{\"type\":\"Balance\",\"value\":\"60295200000000000000\",\"value_raw\":\"\"}]", "event_idx": 1, "extrinsic_hash": "", "block_timestamp": 1598897740}, {"event_index": "1044347-6", "block_num": 1044347, "extrinsic_idx": 6, "module_id": "plasmlockdrop", "event_id": "ClaimComplete", "params": "[{\"type\":\"ClaimId\",\"value\":\"0x91544ae4127c9fb6053e7a0541ae4f1dbbfdb71a854751c09d279cc8951e3e99\",\"value_raw\":\"\"},{\"type\":\"AccountId\",\"value\":\"cba5bddb3efe857edf18b01ea28eef0b49b518c48ea903b5e8f4129af91772ed\",\"value_raw\":\"\"},{\"type\":\"Balance\",\"value\":\"123520000000000000000\",\"value_raw\":\"\"}]", "event_idx": 13, "extrinsic_hash": "", "block_timestamp": 1598897710}, {"event_index": "1044341-1", "block_num": 1044341, "extrinsic_idx": 1, "module_id": "plasmlockdrop", "event_id": "ClaimComplete", "params": "[{\"type\":\"ClaimId\",\"value\":\"0x033400f2e6da0d8b9b144785e9e4087cbe85ea16e0157f389e1ae227709e3901\",\"value_raw\":\"\"},{\"type\":\"AccountId\",\"value\":\"f12b2f3b99ca32233e3cee3fff0d24d6b1f788eee0942a5330697a02b95d6a18\",\"value_raw\":\"\"},{\"type\":\"Balance\",\"value\":\"1552000000000000000000\",\"value_raw\":\"\"}]", "event_idx": 3, "extrinsic_hash": "", "block_timestamp": 1598897650}, {"event_index": "1044318-1", "block_num": 1044318, "extrinsic_idx": 1, "module_id": "plasmlockdrop", "event_id": "ClaimComplete", "params": "[{\"type\":\"ClaimId\",\"value\":\"0x0fe36d77071ae9f38b86e7dd9735f4a73edd68e87e7ba9d764b2e10e70c3712e\",\"value_raw\":\"\"},{\"type\":\"AccountId\",\"value\":\"288cddfe62930c5358f9272b90b974f3a4f2fb3754e9a7b638a01023868c6024\",\"value_raw\":\"\"},{\"type\":\"Balance\",\"value\":\"604800000000000000000\",\"value_raw\":\"\"}]", "event_idx": 3, "extrinsic_hash": "", "block_timestamp": 1598897420}, {"event_index": "1044314-8", "block_num": 1044314, "extrinsic_idx": 8, "module_id": "plasmlockdrop", "event_id": "ClaimComplete", "params": "[{\"type\":\"ClaimId\",\"value\":\"0x9bf8da0d4a92bdfb2a324e35189456b7d5c513cdbb74ce6e1713cd9e17f24dd3\",\"value_raw\":\"\"},{\"type\":\"AccountId\",\"value\":\"ec927e3f2902be19dbdf16e59136931f8ea64d4babc692517692b7045f2a2135\",\"value_raw\":\"\"},{\"type\":\"Balance\",\"value\":\"299200000000000000000\",\"value_raw\":\"\"}]", "event_idx": 15, "extrinsic_hash": "", "block_timestamp": 1598897380}, {"event_index": "1044306-1", "block_num": 1044306, "extrinsic_idx": 1, "module_id": "plasmlockdrop", "event_id": "ClaimComplete", "params": "[{\"type\":\"ClaimId\",\"value\":\"0x4fcb778b0c8544653258bbc9734b2c5ef9bb1146ab3ab18e603dddf8a5b1989c\",\"value_raw\":\"\"},{\"type\":\"AccountId\",\"value\":\"5e094f7124e7cefac9f37f4738ba48f60ddfc8982eb9d7f3bb92cadb1ce8d023\",\"value_raw\":\"\"},{\"type\":\"Balance\",\"value\":\"725560000000000000000\",\"value_raw\":\"\"}]", "event_idx": 3, "extrinsic_hash": "", "block_timestamp": 1598897300}, {"event_index": "1044300-1", "block_num": 1044300, "extrinsic_idx": 1, "module_id": "plasmlockdrop", "event_id": "ClaimComplete", "params": "[{\"type\":\"ClaimId\",\"value\":\"0x8a430767c7bd861bc9b52dbf72c217852a36a80d3a504137df8b0a4417074888\",\"value_raw\":\"\"},{\"type\":\"AccountId\",\"value\":\"1c182c57b14640e9899fec51657a20a27db3c57a1a98a7dc41bba635e064ff26\",\"value_raw\":\"\"},{\"type\":\"Balance\",\"value\":\"104220000000000000000\",\"value_raw\":\"\"}]", "event_idx": 3, "extrinsic_hash": "", "block_timestamp": 1598897240}, {"event_index": "1044300-2", "block_num": 1044300, "extrinsic_idx": 2, "module_id": "plasmlockdrop", "event_id": "ClaimComplete", "params": "[{\"type\":\"ClaimId\",\"value\":\"0x2d1a25f208fcb2107739b6627605fd862acc17430d9521983db6a34355e5557c\",\"value_raw\":\"\"},{\"type\":\"AccountId\",\"value\":\"b4786ddd69d5fcd4818665028fa9ba7c62e9125389b6b752dd21a92f45a3f73c\",\"value_raw\":\"\"},{\"type\":\"Balance\",\"value\":\"14960000000000000000\",\"value_raw\":\"\"}]", "event_idx": 5, "extrinsic_hash": "", "block_timestamp": 1598897240}, {"event_index": "1044293-2", "block_num": 1044293, "extrinsic_idx": 2, "module_id": "plasmlockdrop", "event_id": "ClaimComplete", "params": "[{\"type\":\"ClaimId\",\"value\":\"0xfa25266c23fa550b0ac6931cbfee0c1e19dcbcc33c97bb073f6f4f1b0f1fb44b\",\"value_raw\":\"\"},{\"type\":\"AccountId\",\"value\":\"84dfcaace0bf7fcaef1b946588c2f9ba912b488d4a8d34dacd8b8503f7f64e67\",\"value_raw\":\"\"},{\"type\":\"Balance\",\"value\":\"617600000000000000000\",\"value_raw\":\"\"}]", "event_idx": 5, "extrinsic_hash": "", "block_timestamp": 1598897170}, {"event_index": "1044292-1", "block_num": 1044292, "extrinsic_idx": 1, "module_id": "plasmlockdrop", "event_id": "ClaimComplete", "params": "[{\"type\":\"ClaimId\",\"value\":\"0x59d50fd0dabef8086aa55083522fa5021d7a13142501271174ec7371c5236e12\",\"value_raw\":\"\"},{\"type\":\"AccountId\",\"value\":\"9a44a9758a2f7a51981cb1a909361e691000a3b72014bcd450c0d5a0e64ac231\",\"value_raw\":\"\"},{\"type\":\"Balance\",\"value\":\"12352000000000000000\",\"value_raw\":\"\"}]", "event_idx": 3, "extrinsic_hash": "", "block_timestamp": 1598897160}, {"event_index": "1044291-1", "block_num": 1044291, "extrinsic_idx": 1, "module_id": "plasmlockdrop", "event_id": "ClaimComplete", "params": "[{\"type\":\"ClaimId\",\"value\":\"0xc111bff22323663ee79253af3dd386a7cf193bc9b210f23e780a18ab00f675ab\",\"value_raw\":\"\"},{\"type\":\"AccountId\",\"value\":\"de2e97439b2458e025c264a389a9305b36b5ed8ec488528448ef0edee545fa2b\",\"value_raw\":\"\"},{\"type\":\"Balance\",\"value\":\"3979360000000000000000\",\"value_raw\":\"\"}]", "event_idx": 1, "extrinsic_hash": "", "block_timestamp": 1598897150}, {"event_index": "1044289-3", "block_num": 1044289, "extrinsic_idx": 3, "module_id": "plasmlockdrop", "event_id": "ClaimComplete", "params": "[{\"type\":\"ClaimId\",\"value\":\"0x565a9c6bee3dacac7a92a604978a7f2a4fc2b3ca2358db1e643d55c22fb65529\",\"value_raw\":\"\"},{\"type\":\"AccountId\",\"value\":\"62bf9736c6673e7a2e295779783296310e941387e35011a888a77d3528dd985b\",\"value_raw\":\"\"},{\"type\":\"Balance\",\"value\":\"2992000000000000000000\",\"value_raw\":\"\"}]", "event_idx": 7, "extrinsic_hash": "", "block_timestamp": 1598897130}, {"event_index": "1044265-1", "block_num": 1044265, "extrinsic_idx": 1, "module_id": "plasmlockdrop", "event_id": "ClaimComplete", "params": "[{\"type\":\"ClaimId\",\"value\":\"0xa2ece378781609f28245b1f3761dfba487bae87506ac89fc0957043d52919dbc\",\"value_raw\":\"\"},{\"type\":\"AccountId\",\"value\":\"72c4adefa9d6098fba79e39ba446d13c5e7de39c5442d99bf15f644745295d5b\",\"value_raw\":\"\"},{\"type\":\"Balance\",\"value\":\"23160000000000000000\",\"value_raw\":\"\"}]", "event_idx": 3, "extrinsic_hash": "", "block_timestamp": 1598896890}, {"event_index": "1044246-1", "block_num": 1044246, "extrinsic_idx": 1, "module_id": "plasmlockdrop", "event_id": "ClaimComplete", "params": "[{\"type\":\"ClaimId\",\"value\":\"0xc3318d256526b059e7d6b20b1abf2269b69448f192d4caef8495a0bd89701b0b\",\"value_raw\":\"\"},{\"type\":\"AccountId\",\"value\":\"61d2db510672eadbb16225c297e1a87055fc6a19bbb797b66f4fb70d80773416\",\"value_raw\":\"\"},{\"type\":\"Balance\",\"value\":\"9264000000000000000\",\"value_raw\":\"\"}]", "event_idx": 3, "extrinsic_hash": "", "block_timestamp": 1598896700}, {"event_index": "1044222-1", "block_num": 1044222, "extrinsic_idx": 1, "module_id": "plasmlockdrop", "event_id": "ClaimComplete", "params": "[{\"type\":\"ClaimId\",\"value\":\"0xa63dca04e0444eb20a6eb94b971e951faa6a3da796ba1ff1c4ab4cae8a53aa20\",\"value_raw\":\"\"},{\"type\":\"AccountId\",\"value\":\"ec927e3f2902be19dbdf16e59136931f8ea64d4babc692517692b7045f2a2135\",\"value_raw\":\"\"},{\"type\":\"Balance\",\"value\":\"191070000000000000000\",\"value_raw\":\"\"}]", "event_idx": 3, "extrinsic_hash": "", "block_timestamp": 1598896460}, {"event_index": "1044208-16", "block_num": 1044208, "extrinsic_idx": 16, "module_id": "plasmlockdrop", "event_id": "ClaimComplete", "params": "[{\"type\":\"ClaimId\",\"value\":\"0x2412bb92a5bb2f849234b9582c31beab69fc9d41bac3c85e7e1c97fb306e6024\",\"value_raw\":\"\"},{\"type\":\"AccountId\",\"value\":\"b4786ddd69d5fcd4818665028fa9ba7c62e9125389b6b752dd21a92f45a3f73c\",\"value_raw\":\"\"},{\"type\":\"Balance\",\"value\":\"2316000000000000000\",\"value_raw\":\"\"}]", "event_idx": 33, "extrinsic_hash": "", "block_timestamp": 1598896320}, {"event_index": "1044197-1", "block_num": 1044197, "extrinsic_idx": 1, "module_id": "plasmlockdrop", "event_id": "ClaimComplete", "params": "[{\"type\":\"ClaimId\",\"value\":\"0xed36bbacd63a50360afdef71798672dac7e13aba48a85f88c507bb72e90e2bea\",\"value_raw\":\"\"},{\"type\":\"AccountId\",\"value\":\"0e574c4994050b43e7933b37b581acc704d7661e47234894ff2435465716ad15\",\"value_raw\":\"\"},{\"type\":\"Balance\",\"value\":\"30880000000000000000000\",\"value_raw\":\"\"}]", "event_idx": 1, "extrinsic_hash": "", "block_timestamp": 1598896210}, {"event_index": "1044195-1", "block_num": 1044195, "extrinsic_idx": 1, "module_id": "plasmlockdrop", "event_id": "ClaimComplete", "params": "[{\"type\":\"ClaimId\",\"value\":\"0x27dc8544df171977f9914ec989466e9167386965b40a5d0ae16ebd9b9e16ce81\",\"value_raw\":\"\"},{\"type\":\"AccountId\",\"value\":\"a559a90aba6deb9d9c903fbe0bce2b9b0cdeb164c5d0072240bd0c2f239c00e0\",\"value_raw\":\"\"},{\"type\":\"Balance\",\"value\":\"598400000000000000000\",\"value_raw\":\"\"}]", "event_idx": 3, "extrinsic_hash": "", "block_timestamp": 1598896190}, {"event_index": "1044193-1", "block_num": 1044193, "extrinsic_idx": 1, "module_id": "plasmlockdrop", "event_id": "ClaimComplete", "params": "[{\"type\":\"ClaimId\",\"value\":\"0x89d413f94a6ee64177b6111208aed5bb4553402b1e1240d6a990e11600cfcca7\",\"value_raw\":\"\"},{\"type\":\"AccountId\",\"value\":\"5c42f792049b66edff7169bde4d01ebda54bc24fb8f2dde9abc32d3100408146\",\"value_raw\":\"\"},{\"type\":\"Balance\",\"value\":\"46320000000000000000\",\"value_raw\":\"\"}]", "event_idx": 3, "extrinsic_hash": "", "block_timestamp": 1598896170}, {"event_index": "1044175-2", "block_num": 1044175, "extrinsic_idx": 2, "module_id": "plasmlockdrop", "event_id": "ClaimComplete", "params": "[{\"type\":\"ClaimId\",\"value\":\"0x0fd5ffda61c9d6434ad285d0db6c19394805312501829ff555865e32d2a48ee7\",\"value_raw\":\"\"},{\"type\":\"AccountId\",\"value\":\"945e5366c6b4b53f20baf1e6623c575d7611ad5700ca69c1e8eb054d7435f831\",\"value_raw\":\"\"},{\"type\":\"Balance\",\"value\":\"4632000000000000000\",\"value_raw\":\"\"}]", "event_idx": 5, "extrinsic_hash": "", "block_timestamp": 1598895990}, {"event_index": "1044168-1", "block_num": 1044168, "extrinsic_idx": 1, "module_id": "plasmlockdrop", "event_id": "ClaimComplete", "params": "[{\"type\":\"ClaimId\",\"value\":\"0xe7fda9b6a1e32b9c97a022f5be85bdea171940b7c38cbb646bf44792214bf9b3\",\"value_raw\":\"\"},{\"type\":\"AccountId\",\"value\":\"6ca2601b291468968d2463eb614cdd6f7bcaf3e89e4e79210eda3a66f6fadc7e\",\"value_raw\":\"\"},{\"type\":\"Balance\",\"value\":\"1389600000000000000000\",\"value_raw\":\"\"}]", "event_idx": 1, "extrinsic_hash": "", "block_timestamp": 1598895920}, {"event_index": "1044165-1", "block_num": 1044165, "extrinsic_idx": 1, "module_id": "plasmlockdrop", "event_id": "ClaimComplete", "params": "[{\"type\":\"ClaimId\",\"value\":\"0xefd0350fe16a82dc2533544ec1b89854533eb7f589194d52b247c2f06eacee2c\",\"value_raw\":\"\"},{\"type\":\"AccountId\",\"value\":\"664d1e27563ddcc81acc97d454431fc0beba4ce643bf25f300b97e6eb90747c9\",\"value_raw\":\"\"},{\"type\":\"Balance\",\"value\":\"1544000000000000000000\",\"value_raw\":\"\"}]", "event_idx": 3, "extrinsic_hash": "", "block_timestamp": 1598895890}, {"event_index": "1044154-1", "block_num": 1044154, "extrinsic_idx": 1, "module_id": "plasmlockdrop", "event_id": "ClaimComplete", "params": "[{\"type\":\"ClaimId\",\"value\":\"0xbf192d8e83d2e1310249ddb472640c6aeb1fafb2b39457d753d3297496482a1d\",\"value_raw\":\"\"},{\"type\":\"AccountId\",\"value\":\"605263029664eee9d34649fea19b911dafbd5dadb085cf0b54fb3f5ff03eb77d\",\"value_raw\":\"\"},{\"type\":\"Balance\",\"value\":\"1235200000000000000000\",\"value_raw\":\"\"}]", "event_idx": 3, "extrinsic_hash": "", "block_timestamp": 1598895780}]}}