{"code": 0, "message": "Success", "ttl": 1, "data": {"count": 2053, "events": [{"event_index": "1102237-2", "block_num": 1102237, "extrinsic_idx": 2, "module_id": "plasmlockdrop", "event_id": "ClaimComplete", "params": "[{\"type\":\"ClaimId\",\"value\":\"0xdb4046ac89a896a7405cc5430bee4c6ceb1cc42fac821ef2ceabd54eb0620ea3\",\"value_raw\":\"\"},{\"type\":\"AccountId\",\"value\":\"fc8b9ba6bb2ce0fd78e5de3f3f121587a492dd3d273cce0fff50e1c80311ba7d\",\"value_raw\":\"\"},{\"type\":\"Balance\",\"value\":\"14900000000000000000\",\"value_raw\":\"\"}]", "event_idx": 4, "extrinsic_hash": "", "block_timestamp": 1599482580}, {"event_index": "1102220-2", "block_num": 1102220, "extrinsic_idx": 2, "module_id": "plasmlockdrop", "event_id": "ClaimComplete", "params": "[{\"type\":\"ClaimId\",\"value\":\"0x0e9bb73588c117b985d6e686026aa7dbb0691a0f257bdb1252ce2c14cdda5599\",\"value_raw\":\"\"},{\"type\":\"AccountId\",\"value\":\"f4196fb01a41f958f5fb871a587d99b595acce46d0dc48d8c82318e4bc1ea622\",\"value_raw\":\"\"},{\"type\":\"Balance\",\"value\":\"149000000000000000000\",\"value_raw\":\"\"}]", "event_idx": 4, "extrinsic_hash": "", "block_timestamp": 1599482410}, {"event_index": "1102192-1", "block_num": 1102192, "extrinsic_idx": 1, "module_id": "plasmlockdrop", "event_id": "ClaimComplete", "params": "[{\"type\":\"ClaimId\",\"value\":\"0xaec249ab2aca766aaad4043b30dbcea7a12bb5d89fa7ab98cd2dd573c0316730\",\"value_raw\":\"\"},{\"type\":\"AccountId\",\"value\":\"7bed682f09c5a6756a78b365ae692e480f3782fc9687ab51f167da3272a9dc98\",\"value_raw\":\"\"},{\"type\":\"Balance\",\"value\":\"83440000000000000000\",\"value_raw\":\"\"}]", "event_idx": 3, "extrinsic_hash": "", "block_timestamp": 1599482130}, {"event_index": "1102118-2", "block_num": 1102118, "extrinsic_idx": 2, "module_id": "plasmlockdrop", "event_id": "ClaimComplete", "params": "[{\"type\":\"ClaimId\",\"value\":\"0x2f3c50b18cd4992f31187fe50b302858a239f51d968c2431f280c81306167bf2\",\"value_raw\":\"\"},{\"type\":\"AccountId\",\"value\":\"e39154cfc1d029114b1ced9ce42b7feeef48df91306f84a8f4c15998b5728f20\",\"value_raw\":\"\"},{\"type\":\"Balance\",\"value\":\"4620000000000000000\",\"value_raw\":\"\"}]", "event_idx": 2, "extrinsic_hash": "", "block_timestamp": 1599481390}, {"event_index": "1102106-43", "block_num": 1102106, "extrinsic_idx": 43, "module_id": "plasmlockdrop", "event_id": "ClaimComplete", "params": "[{\"type\":\"ClaimId\",\"value\":\"0x9b83a069dd658b6e8b0898e9bf0b02423922a554049cbe7bf42f4792945e3c7c\",\"value_raw\":\"\"},{\"type\":\"AccountId\",\"value\":\"d931db654bf3567f6bc91af14215c2b9b31af60c96f4409bbc7a1a4379be1584\",\"value_raw\":\"\"},{\"type\":\"Balance\",\"value\":\"48000000000000000000\",\"value_raw\":\"\"}]", "event_idx": 86, "extrinsic_hash": "", "block_timestamp": 1599481270}, {"event_index": "1102081-3", "block_num": 1102081, "extrinsic_idx": 3, "module_id": "plasmlockdrop", "event_id": "ClaimComplete", "params": "[{\"type\":\"ClaimId\",\"value\":\"0x0c6f1291c65cfaf94a6742da88083ebc572ca6149530b74175985fdfea109c10\",\"value_raw\":\"\"},{\"type\":\"AccountId\",\"value\":\"089f1a8d0514da8150aa20a136e1575254c9f1b0d5b464b8c520ba5490838124\",\"value_raw\":\"\"},{\"type\":\"Balance\",\"value\":\"240000000000000000000\",\"value_raw\":\"\"}]", "event_idx": 5, "extrinsic_hash": "", "block_timestamp": 1599481010}, {"event_index": "1102074-1", "block_num": 1102074, "extrinsic_idx": 1, "module_id": "plasmlockdrop", "event_id": "ClaimComplete", "params": "[{\"type\":\"ClaimId\",\"value\":\"0x251d5940ca6e4a0949cc19455168fbee10f223dd7691eeaab793b77819f4386f\",\"value_raw\":\"\"},{\"type\":\"AccountId\",\"value\":\"c7dbd17a0e8ae59a19b06c4afc71f123bd9b0663358c398c23333a5c20b301b0\",\"value_raw\":\"\"},{\"type\":\"Balance\",\"value\":\"108000000000000000000\",\"value_raw\":\"\"}]", "event_idx": 1, "extrinsic_hash": "", "block_timestamp": 1599480940}, {"event_index": "1102071-2", "block_num": 1102071, "extrinsic_idx": 2, "module_id": "plasmlockdrop", "event_id": "ClaimComplete", "params": "[{\"type\":\"ClaimId\",\"value\":\"0x5b03aa103578e27dc23afbc93e2afdf29b9b40836f6ff6d148e5819ea7c48376\",\"value_raw\":\"\"},{\"type\":\"AccountId\",\"value\":\"e39154cfc1d029114b1ced9ce42b7feeef48df91306f84a8f4c15998b5728f20\",\"value_raw\":\"\"},{\"type\":\"Balance\",\"value\":\"180000000000000000\",\"value_raw\":\"\"}]", "event_idx": 2, "extrinsic_hash": "", "block_timestamp": 1599480910}, {"event_index": "1102069-1", "block_num": 1102069, "extrinsic_idx": 1, "module_id": "plasmlockdrop", "event_id": "ClaimComplete", "params": "[{\"type\":\"ClaimId\",\"value\":\"0x2a3e63e5da766916f5b4f97263792b315402be3337544b7ee4f1deb9934dc2fc\",\"value_raw\":\"\"},{\"type\":\"AccountId\",\"value\":\"e39154cfc1d029114b1ced9ce42b7feeef48df91306f84a8f4c15998b5728f20\",\"value_raw\":\"\"},{\"type\":\"Balance\",\"value\":\"369600000000000000\",\"value_raw\":\"\"}]", "event_idx": 3, "extrinsic_hash": "", "block_timestamp": 1599480890}, {"event_index": "1102051-6", "block_num": 1102051, "extrinsic_idx": 6, "module_id": "plasmlockdrop", "event_id": "ClaimComplete", "params": "[{\"type\":\"ClaimId\",\"value\":\"0x38ef4e94d0e76e32fc1f8718cc397ed880961fbe25edeac67ba9c86a121cbb35\",\"value_raw\":\"\"},{\"type\":\"AccountId\",\"value\":\"480fad96193c9172e6022301ac7f1f87b475503b80c0482f756897ec076db438\",\"value_raw\":\"\"},{\"type\":\"Balance\",\"value\":\"536400000000000000000\",\"value_raw\":\"\"}]", "event_idx": 13, "extrinsic_hash": "", "block_timestamp": 1599480710}, {"event_index": "1101968-1", "block_num": 1101968, "extrinsic_idx": 1, "module_id": "plasmlockdrop", "event_id": "ClaimComplete", "params": "[{\"type\":\"ClaimId\",\"value\":\"0x6334ac11237a1be03191b895899b56642d3fb9b25258e4e06f5393a2e63d6181\",\"value_raw\":\"\"},{\"type\":\"AccountId\",\"value\":\"e6639cbac3f7dea4633307ba2882f25d8cc423f9a73bc4ecd07929f074f36b5a\",\"value_raw\":\"\"},{\"type\":\"Balance\",\"value\":\"548320000000000000000\",\"value_raw\":\"\"}]", "event_idx": 1, "extrinsic_hash": "", "block_timestamp": 1599479880}, {"event_index": "1101945-1", "block_num": 1101945, "extrinsic_idx": 1, "module_id": "plasmlockdrop", "event_id": "ClaimComplete", "params": "[{\"type\":\"ClaimId\",\"value\":\"0x3946919c42f5d6cd7629f5f3561d3a7412068ce4d17c00e7cc7db8ff7bf1abd3\",\"value_raw\":\"\"},{\"type\":\"AccountId\",\"value\":\"5c011b42b76bedaf2adb2270ad9d2082adeb6bc3ac2fda0224b612bf96755673\",\"value_raw\":\"\"},{\"type\":\"Balance\",\"value\":\"150000000000000000000\",\"value_raw\":\"\"}]", "event_idx": 3, "extrinsic_hash": "", "block_timestamp": 1599479650}, {"event_index": "1101860-2", "block_num": 1101860, "extrinsic_idx": 2, "module_id": "plasmlockdrop", "event_id": "ClaimComplete", "params": "[{\"type\":\"ClaimId\",\"value\":\"0xd1be628fef4740dc34bbbeab83885612e533ea393ad7ff987b3f1029bce28d7e\",\"value_raw\":\"\"},{\"type\":\"AccountId\",\"value\":\"18f3c1f77cedfc6335f554e033314956eef3c45b77e64c71d6318ad230eabe71\",\"value_raw\":\"\"},{\"type\":\"Balance\",\"value\":\"3825000000000000000\",\"value_raw\":\"\"}]", "event_idx": 5, "extrinsic_hash": "", "block_timestamp": 1599478800}, {"event_index": "1101788-1", "block_num": 1101788, "extrinsic_idx": 1, "module_id": "plasmlockdrop", "event_id": "ClaimComplete", "params": "[{\"type\":\"ClaimId\",\"value\":\"0xece45468a133ae1b25955fcf2808210ff6280caaae44ca0883284efed0b56642\",\"value_raw\":\"\"},{\"type\":\"AccountId\",\"value\":\"84e020b9d81de5a95c69cf1cb5ad31996934b1423fbd69bf3141707f18855c0d\",\"value_raw\":\"\"},{\"type\":\"Balance\",\"value\":\"220320000000000000000\",\"value_raw\":\"\"}]", "event_idx": 3, "extrinsic_hash": "", "block_timestamp": 1599478080}, {"event_index": "1101781-1", "block_num": 1101781, "extrinsic_idx": 1, "module_id": "plasmlockdrop", "event_id": "ClaimComplete", "params": "[{\"type\":\"ClaimId\",\"value\":\"0xe330045f4d1b571c372cc8ab82422c72815c7bb319b1b6da2ffbf2e9e1f2c9bd\",\"value_raw\":\"\"},{\"type\":\"AccountId\",\"value\":\"9c6b4fa96ecd45c0b2853fec604bf4a7405ab7dc1a4bf9601780bfde45bb9a39\",\"value_raw\":\"\"},{\"type\":\"Balance\",\"value\":\"2203200000000000000000\",\"value_raw\":\"\"}]", "event_idx": 1, "extrinsic_hash": "", "block_timestamp": 1599478010}, {"event_index": "1101773-1", "block_num": 1101773, "extrinsic_idx": 1, "module_id": "plasmlockdrop", "event_id": "ClaimComplete", "params": "[{\"type\":\"ClaimId\",\"value\":\"0x98ca48afe97aca66e41d70c18e09cfcc16c77a2498871d213d19dbacdf4e3f51\",\"value_raw\":\"\"},{\"type\":\"AccountId\",\"value\":\"9e4cb50134f822e1829e4c421f18596bc973355472971dc2a731f8916b3cdb74\",\"value_raw\":\"\"},{\"type\":\"Balance\",\"value\":\"244800000000000000000\",\"value_raw\":\"\"}]", "event_idx": 3, "extrinsic_hash": "", "block_timestamp": 1599477930}, {"event_index": "1101735-2", "block_num": 1101735, "extrinsic_idx": 2, "module_id": "plasmlockdrop", "event_id": "ClaimComplete", "params": "[{\"type\":\"ClaimId\",\"value\":\"0xaee3152b90261075153a66255dbf559c624a96d4ef6fdfa4709879e9bc244618\",\"value_raw\":\"\"},{\"type\":\"AccountId\",\"value\":\"0792f5e3eedd5dc149b4ce30f79d3aed4effbd5e6b2d381add19a01d6d2cb760\",\"value_raw\":\"\"},{\"type\":\"Balance\",\"value\":\"2386800000000000000000\",\"value_raw\":\"\"}]", "event_idx": 4, "extrinsic_hash": "", "block_timestamp": 1599477550}, {"event_index": "1101635-1", "block_num": 1101635, "extrinsic_idx": 1, "module_id": "plasmlockdrop", "event_id": "ClaimComplete", "params": "[{\"type\":\"ClaimId\",\"value\":\"0x27f3ddd25681cf82b0f19086e2136565c8289f27e91935ada135cca0935922b6\",\"value_raw\":\"\"},{\"type\":\"AccountId\",\"value\":\"decf9fa50c5b523c9a1d6cbf14e3cded6e8282723021944d401a181b32a45f46\",\"value_raw\":\"\"},{\"type\":\"Balance\",\"value\":\"306000000000000000000\",\"value_raw\":\"\"}]", "event_idx": 3, "extrinsic_hash": "", "block_timestamp": 1599476550}, {"event_index": "1101622-1", "block_num": 1101622, "extrinsic_idx": 1, "module_id": "plasmlockdrop", "event_id": "ClaimComplete", "params": "[{\"type\":\"ClaimId\",\"value\":\"0x56b568dd5e79440197f0a7940a7c5917a7686ad134a193331fa8fb93ca0c7b60\",\"value_raw\":\"\"},{\"type\":\"AccountId\",\"value\":\"e6639cbac3f7dea4633307ba2882f25d8cc423f9a73bc4ecd07929f074f36b5a\",\"value_raw\":\"\"},{\"type\":\"Balance\",\"value\":\"48960000000000000000\",\"value_raw\":\"\"}]", "event_idx": 3, "extrinsic_hash": "", "block_timestamp": 1599476420}, {"event_index": "1101579-2", "block_num": 1101579, "extrinsic_idx": 2, "module_id": "plasmlockdrop", "event_id": "ClaimComplete", "params": "[{\"type\":\"ClaimId\",\"value\":\"0x6ec7e85a6bc622b81604da4dae59b0ca817db99b75475b31e7da9d789397bc6a\",\"value_raw\":\"\"},{\"type\":\"AccountId\",\"value\":\"6094cbaf18261c25142c39bcbc2a99394607455a2fac101a4f5baff99723482b\",\"value_raw\":\"\"},{\"type\":\"Balance\",\"value\":\"3672000000000000000\",\"value_raw\":\"\"}]", "event_idx": 5, "extrinsic_hash": "", "block_timestamp": 1599475990}, {"event_index": "1101513-2", "block_num": 1101513, "extrinsic_idx": 2, "module_id": "plasmlockdrop", "event_id": "ClaimComplete", "params": "[{\"type\":\"ClaimId\",\"value\":\"0x5f4cf091bd46f568c341439170b3670ef90fef90d187013b63f5c63f55c183dc\",\"value_raw\":\"\"},{\"type\":\"AccountId\",\"value\":\"6459c49fccb6c8c1f20fbc0565f348382989572e4d3c1d039adbabee864b0b49\",\"value_raw\":\"\"},{\"type\":\"Balance\",\"value\":\"73920000000000000000\",\"value_raw\":\"\"}]", "event_idx": 5, "extrinsic_hash": "", "block_timestamp": 1599475330}, {"event_index": "1101503-1", "block_num": 1101503, "extrinsic_idx": 1, "module_id": "plasmlockdrop", "event_id": "ClaimComplete", "params": "[{\"type\":\"ClaimId\",\"value\":\"0x863c37eb8e5b2212c35a31584206f3b66ea4efb7e0eb53c10aa204f889a58d40\",\"value_raw\":\"\"},{\"type\":\"AccountId\",\"value\":\"172b891f0c75b843eaf9935b6762c40ced4ddc89ef09cd10e7f8f7f9d1c8829c\",\"value_raw\":\"\"},{\"type\":\"Balance\",\"value\":\"62000000000000000000\",\"value_raw\":\"\"}]", "event_idx": 3, "extrinsic_hash": "", "block_timestamp": 1599475230}, {"event_index": "1101487-1", "block_num": 1101487, "extrinsic_idx": 1, "module_id": "plasmlockdrop", "event_id": "ClaimComplete", "params": "[{\"type\":\"ClaimId\",\"value\":\"0x5ee754f8ed07b2e985a84100a3f59af722f67193a9d7af9d0d7219e9c431b545\",\"value_raw\":\"\"},{\"type\":\"AccountId\",\"value\":\"31e1ca07193bbff0e21239dabf63634a6c8f6d687fa8dac51a56976c2c1071ab\",\"value_raw\":\"\"},{\"type\":\"Balance\",\"value\":\"947360000000000000000\",\"value_raw\":\"\"}]", "event_idx": 3, "extrinsic_hash": "", "block_timestamp": 1599475070}, {"event_index": "1101481-2", "block_num": 1101481, "extrinsic_idx": 2, "module_id": "plasmlockdrop", "event_id": "ClaimComplete", "params": "[{\"type\":\"ClaimId\",\"value\":\"0xf8469a33b8ff52dfcb5f2331b16428967247cf1ee3b2da55b6cdbeb6fe9c1ad6\",\"value_raw\":\"\"},{\"type\":\"AccountId\",\"value\":\"201a00e0b1d2ac5e8cd4e81412360b5b569b8fa3b66f05e9498ebe3690fe107e\",\"value_raw\":\"\"},{\"type\":\"Balance\",\"value\":\"168300000000000000000\",\"value_raw\":\"\"}]", "event_idx": 4, "extrinsic_hash": "", "block_timestamp": 1599475010}, {"event_index": "1101478-13", "block_num": 1101478, "extrinsic_idx": 13, "module_id": "plasmlockdrop", "event_id": "ClaimComplete", "params": "[{\"type\":\"ClaimId\",\"value\":\"0x3a45977b711567efac8b3d2ca0a123fb891f3d76539473b9bbb0c2405190055e\",\"value_raw\":\"\"},{\"type\":\"AccountId\",\"value\":\"5453e79a120c60bf7ea47b45aaebf886a2af93164bd4728e05b8b067f8b07b1e\",\"value_raw\":\"\"},{\"type\":\"Balance\",\"value\":\"19250000000000000000\",\"value_raw\":\"\"}]", "event_idx": 27, "extrinsic_hash": "", "block_timestamp": 1599474980}]}}